notionaut/__init__.py
notionaut/client.py
notionaut-0.2.4.dist-info/METADATA
notionaut-0.2.4.dist-info/WHEEL
notionaut-0.2.4.dist-info/RECORD
