Metadata-Version: 2.1
Name: notionaut
Version: 0.2.4
Summary: A simple package for fetching Notion databases as pandas dataframes
Home-page: https://github.com/nschenone/notionaut
License: MIT
Author: Nick Schenone
Author-email: nschenone16@gmail.com
Requires-Python: >=3.9,<4.0
Classifier: License :: OSI Approved :: MIT License
Classifier: Programming Language :: Python :: 3
Classifier: Programming Language :: Python :: 3.9
Classifier: Programming Language :: Python :: 3.10
Classifier: Programming Language :: Python :: 3.11
Classifier: Programming Language :: Python :: 3.12
Requires-Dist: notion-client (>=1.0.0,<2.0.0)
Requires-Dist: numpy (<2.0)
Requires-Dist: pandas (>=2.3.0,<3.0.0)
Project-URL: Repository, https://github.com/nschenone/notionaut
